seekerfree/__init__.py
seekerfree/seekerfree.cpython-311-linux.so
seekerfree/seekerfree.py
seekerfree/bin/coll
seekerfree/bin/coll-linux
seekerfree/scripts/darwin_seekeragg.sh
seekerfree/scripts/seekeragg.sh
insideopt_gains-0.0.9.dist-info/AUTHORS.rst
insideopt_gains-0.0.9.dist-info/LICENSE.rst
insideopt_gains-0.0.9.dist-info/METADATA
insideopt_gains-0.0.9.dist-info/WHEEL
insideopt_gains-0.0.9.dist-info/top_level.txt
insideopt_gains-0.0.9.dist-info/RECORD
